quadcopter_interface/ip/PWM/dshot_out.v
`default_nettype none
`timescale 1 ns / 1 ns

module dhot_output #(
		parameter update_guardtime = 1000000, //1 second 
		parameter clockFrequency = 50000000
	) (
		input  wire        i_clk,          //       clock.clk
		input  wire        i_reset,        //       reset.reset
		input  wire [15:0] i_pwm_low_value,     //      avs_s0.address
		input  wire [15:0] i_pwm_high_value,
		input  wire        i_write,       //            .write
		output wire	   o_pwm
	);
	


/* state machine state of single bit */
localparam [3:0] INIT_TIME  = 4'h0,
		 		HIGH_TIME   = 4'h1,
	     		LOW_TIME    = 4'h2,
		 		IDLE_	    = 4'h3;
		
						 
//localparam [15:0] LOW_HIGH_TIME = 125;
//localparam [15:0] LOW_LOW_TIME = 209;

//localparam [15:0] HIGH_HIGH_TIME = 250;
//localparam [15:0] HIGH_LOW_TIME = 84;

localparam [15:0] LOW_HIGH_TIME = 117;
localparam [15:0] LOW_LOW_TIME = 215;

localparam [15:0] HIGH_HIGH_TIME = 232;
localparam [15:0] HIGH_LOW_TIME = 100;

/* number of bits to shift */
localparam [3:0] NUM_BIT_TO_SHIFT = 15;

reg [3:0] state;
reg [4:0] bits_to_shift;
reg [15:0] counter_high;
reg [15:0] counter_low;

reg [15:0] dshot_command;
reg bit;

reg pwm;


always @(posedge i_clk or posedge i_reset) begin	

	if (i_reset) begin
			state <= IDLE_;
			bits_to_shift <= 0;
			dshot_command <= 0;
			pwm <= 0;
	end
	else begin
		/* update pwm value */
		if (i_write) begin
			if (bits_to_shift == 0) begin		
				dshot_command <= i_pwm_low_value;
				bits_to_shift <= NUM_BIT_TO_SHIFT;
				bit <= dshot_command[15];
				state <= INIT_TIME;
				$display ("update %X", i_pwm_low_value);
			end
		end
		else begin
			case (state)
				INIT_TIME: begin
					$display ("INIT_TIME 0x%X", dshot_command);
					if (dshot_command[15]) begin
						counter_high = HIGH_HIGH_TIME;
						counter_low = HIGH_LOW_TIME;
					end
					else begin
						counter_high = LOW_HIGH_TIME;
						counter_low = LOW_LOW_TIME;
					end
					state <= HIGH_TIME;
				end

				HIGH_TIME: begin
					pwm <= 1;
					if (counter_high == 0)	begin
						state <= LOW_TIME;
					end
					else			
						counter_high <= counter_high -1;

				end
				LOW_TIME: begin
					
					pwm <= 0;
					if (counter_low == 0) begin
						if ( bits_to_shift == 0) begin
							state = IDLE_;
							$display("DONE  Complete ");
						end
						else begin
							bits_to_shift <= bits_to_shift -1;
						  	dshot_command <= { dshot_command[14:0], 1'b0 };
						  	state <= INIT_TIME;
						end
					end
					else
						counter_low <= counter_low - 1;
					
				end
				IDLE_: begin
				end
		
				default: pwm <= 0;
			endcase
		
		end
	end
	
end
assign o_pwm = pwm;

endmodule
//END of modules

quadcopter_interface/ip/PWM/dshot_tb.v
`default_nettype none
`timescale 1 ns / 1 ns
/* https://iverilog.fandom.com/wiki/Getting_Started */

module test;



  /* Make a reset that pulses once. */
  reg i_reset = 0;
  reg i_clk = 0;
  reg [15:0] low = 16'hAA20;
  reg [15:0] high = 16'hAA55;
  reg i_write = 0 ;
  wire o_pwm;

  initial begin
     $dumpfile("test.vcd");
     $dumpvars(0,test);
     # 10 i_reset = 1;
     # 10 i_reset = 0;
     # 1 i_write = 1;
     # 1 i_write = 0;
     # 10689 $finish;
  end

  /* Make a regular pulsing clock. */

  always #1 i_clk = !i_clk;


dhot_output motor_1(	.i_clk(i_clk),
			.i_reset(i_reset),
			.i_pwm_low_value(low),
			.i_pwm_high_value(high),
			.i_write(i_write),
			.o_pwm(o_pwm));
			
  /* Make a reset that pulses once. */  
  initial
     $monitor("At time %t, value = %h", $time, o_pwm, );

		


endmodule
//eof

quadcopter_interface/ip/PWM/test.vcd
$date
	Fri Feb 21 22:58:36 2020
$end
$version
	Icarus Verilog
$end
$timescale
	1ns
$end
$scope module test $end
$var wire 1 ! o_pwm $end
$var reg 16 " high [15:0] $end
$var reg 1 # i_clk $end
$var reg 1 $ i_reset $end
$var reg 1 % i_write $end
$var reg 16 & low [15:0] $end
$scope module motor_1 $end
$var wire 1 # i_clk $end
$var wire 16 ' i_pwm_high_value [15:0] $end
$var wire 16 ( i_pwm_low_value [15:0] $end
$var wire 1 $ i_reset $end
$var wire 1 % i_write $end
$var wire 1 ! o_pwm $end
$var reg 1 ) bit $end
$var reg 5 * bits_to_shift [4:0] $end
$var reg 16 + counter_high [15:0] $end
$var reg 16 , counter_low [15:0] $end
$var reg 16 - dshot_command [15:0] $end
$var reg 1 . pwm $end
$var reg 4 / state [3:0] $end
$upscope $end
$upscope $end
$enddefinitions $end
#0
$dumpvars
bx /
x.
bx -
bx ,
bx +
bx *
x)
b1010101000100000 (
b1010101001010101 '
b1010101000100000 &
0%
0$
0#
b1010101001010101 "
x!
$end
#1
0!
0.
1#
#2
0#
#3
1#
#4
0#
#5
1#
#6
0#
#7
1#
#8
0#
#9
1#
#10
b0 -
b0 *
b11 /
0#
1$
#11
1#
#12
0#
#13
1#
#14
0#
#15
1#
#16
0#
#17
1#
#18
0#
#19
1#
#20
0#
0$
#21
b0 /
0)
b1111 *
b1010101000100000 -
1#
1%
#22
0#
0%
#23
b1 /
b1010100 ,
b11111010 +
1#
#24
0#
#25
b11111001 +
1!
1.
1#
#26
0#
#27
b11111000 +
1#
#28
0#
#29
b11110111 +
1#
#30
0#
#31
b11110110 +
1#
#32
0#
#33
b11110101 +
1#
#34
0#
#35
b11110100 +
1#
#36
0#
#37
b11110011 +
1#
#38
0#
#39
b11110010 +
1#
#40
0#
#41
b11110001 +
1#
#42
0#
#43
b11110000 +
1#
#44
0#
#45
b11101111 +
1#
#46
0#
#47
b11101110 +
1#
#48
0#
#49
b11101101 +
1#
#50
0#
#51
b11101100 +
1#
#52
0#
#53
b11101011 +
1#
#54
0#
#55
b11101010 +
1#
#56
0#
#57
b11101001 +
1#
#58
0#
#59
b11101000 +
1#
#60
0#
#61
b11100111 +
1#
#62
0#
#63
b11100110 +
1#
#64
0#
#65
b11100101 +
1#
#66
0#
#67
b11100100 +
1#
#68
0#
#69
b11100011 +
1#
#70
0#
#71
b11100010 +
1#
#72
0#
#73
b11100001 +
1#
#74
0#
#75
b11100000 +
1#
#76
0#
#77
b11011111 +
1#
#78
0#
#79
b11011110 +
1#
#80
0#
#81
b11011101 +
1#
#82
0#
#83
b11011100 +
1#
#84
0#
#85
b11011011 +
1#
#86
0#
#87
b11011010 +
1#
#88
0#
#89
b11011001 +
1#
#90
0#
#91
b11011000 +
1#
#92
0#
#93
b11010111 +
1#
#94
0#
#95
b11010110 +
1#
#96
0#
#97
b11010101 +
1#
#98
0#
#99
b11010100 +
1#
#100
0#
#101
b11010011 +
1#
#102
0#
#103
b11010010 +
1#
#104
0#
#105
b11010001 +
1#
#106
0#
#107
b11010000 +
1#
#108
0#
#109
b11001111 +
1#
#110
0#
#111
b11001110 +
1#
#112
0#
#113
b11001101 +
1#
#114
0#
#115
b11001100 +
1#
#116
0#
#117
b11001011 +
1#
#118
0#
#119
b11001010 +
1#
#120
0#
#121
b11001001 +
1#
#122
0#
#123
b11001000 +
1#
#124
0#
#125
b11000111 +
1#
#126
0#
#127
b11000110 +
1#
#128
0#
#129
b11000101 +
1#
#130
0#
#131
b11000100 +
1#
#132
0#
#133
b11000011 +
1#
#134
0#
#135
b11000010 +
1#
#136
0#
#137
b11000001 +
1#
#138
0#
#139
b11000000 +
1#
#140
0#
#141
b10111111 +
1#
#142
0#
#143
b10111110 +
1#
#144
0#
#145
b10111101 +
1#
#146
0#
#147
b10111100 +
1#
#148
0#
#149
b10111011 +
1#
#150
0#
#151
b10111010 +
1#
#152
0#
#153
b10111001 +
1#
#154
0#
#155
b10111000 +
1#
#156
0#
#157
b10110111 +
1#
#158
0#
#159
b10110110 +
1#
#160
0#
#161
b10110101 +
1#
#162
0#
#163
b10110100 +
1#
#164
0#
#165
b10110011 +
1#
#166
0#
#167
b10110010 +
1#
#168
0#
#169
b10110001 +
1#
#170
0#
#171
b10110000 +
1#
#172
0#
#173
b10101111 +
1#
#174
0#
#175
b10101110 +
1#
#176
0#
#177
b10101101 +
1#
#178
0#
#179
b10101100 +
1#
#180
0#
#181
b10101011 +
1#
#182
0#
#183
b10101010 +
1#
#184
0#
#185
b10101001 +
1#
#186
0#
#187
b10101000 +
1#
#188
0#
#189
b10100111 +
1#
#190
0#
#191
b10100110 +
1#
#192
0#
#193
b10100101 +
1#
#194
0#
#195
b10100100 +
1#
#196
0#
#197
b10100011 +
1#
#198
0#
#199
b10100010 +
1#
#200
0#
#201
b10100001 +
1#
#202
0#
#203
b10100000 +
1#
#204
0#
#205
b10011111 +
1#
#206
0#
#207
b10011110 +
1#
#208
0#
#209
b10011101 +
1#
#210
0#
#211
b10011100 +
1#
#212
0#
#213
b10011011 +
1#
#214
0#
#215
b10011010 +
1#
#216
0#
#217
b10011001 +
1#
#218
0#
#219
b10011000 +
1#
#220
0#
#221
b10010111 +
1#
#222
0#
#223
b10010110 +
1#
#224
0#
#225
b10010101 +
1#
#226
0#
#227
b10010100 +
1#
#228
0#
#229
b10010011 +
1#
#230
0#
#231
b10010010 +
1#
#232
0#
#233
b10010001 +
1#
#234
0#
#235
b10010000 +
1#
#236
0#
#237
b10001111 +
1#
#238
0#
#239
b10001110 +
1#
#240
0#
#241
b10001101 +
1#
#242
0#
#243
b10001100 +
1#
#244
0#
#245
b10001011 +
1#
#246
0#
#247
b10001010 +
1#
#248
0#
#249
b10001001 +
1#
#250
0#
#251
b10001000 +
1#
#252
0#
#253
b10000111 +
1#
#254
0#
#255
b10000110 +
1#
#256
0#
#257
b10000101 +
1#
#258
0#
#259
b10000100 +
1#
#260
0#
#261
b10000011 +
1#
#262
0#
#263
b10000010 +
1#
#264
0#
#265
b10000001 +
1#
#266
0#
#267
b10000000 +
1#
#268
0#
#269
b1111111 +
1#
#270
0#
#271
b1111110 +
1#
#272
0#
#273
b1111101 +
1#
#274
0#
#275
b1111100 +
1#
#276
0#
#277
b1111011 +
1#
#278
0#
#279
b1111010 +
1#
#280
0#
#281
b1111001 +
1#
#282
0#
#283
b1111000 +
1#
#284
0#
#285
b1110111 +
1#
#286
0#
#287
b1110110 +
1#
#288
0#
#289
b1110101 +
1#
#290
0#
#291
b1110100 +
1#
#292
0#
#293
b1110011 +
1#
#294
0#
#295
b1110010 +
1#
#296
0#
#297
b1110001 +
1#
#298
0#
#299
b1110000 +
1#
#300
0#
#301
b1101111 +
1#
#302
0#
#303
b1101110 +
1#
#304
0#
#305
b1101101 +
1#
#306
0#
#307
b1101100 +
1#
#308
0#
#309
b1101011 +
1#
#310
0#
#311
b1101010 +
1#
#312
0#
#313
b1101001 +
1#
#314
0#
#315
b1101000 +
1#
#316
0#
#317
b1100111 +
1#
#318
0#
#319
b1100110 +
1#
#320
0#
#321
b1100101 +
1#
#322
0#
#323
b1100100 +
1#
#324
0#
#325
b1100011 +
1#
#326
0#
#327
b1100010 +
1#
#328
0#
#329
b1100001 +
1#
#330
0#
#331
b1100000 +
1#
#332
0#
#333
b1011111 +
1#
#334
0#
#335
b1011110 +
1#
#336
0#
#337
b1011101 +
1#
#338
0#
#339
b1011100 +
1#
#340
0#
#341
b1011011 +
1#
#342
0#
#343
b1011010 +
1#
#344
0#
#345
b1011001 +
1#
#346
0#
#347
b1011000 +
1#
#348
0#
#349
b1010111 +
1#
#350
0#
#351
b1010110 +
1#
#352
0#
#353
b1010101 +
1#
#354
0#
#355
b1010100 +
1#
#356
0#
#357
b1010011 +
1#
#358
0#
#359
b1010010 +
1#
#360
0#
#361
b1010001 +
1#
#362
0#
#363
b1010000 +
1#
#364
0#
#365
b1001111 +
1#
#366
0#
#367
b1001110 +
1#
#368
0#
#369
b1001101 +
1#
#370
0#
#371
b1001100 +
1#
#372
0#
#373
b1001011 +
1#
#374
0#
#375
b1001010 +
1#
#376
0#
#377
b1001001 +
1#
#378
0#
#379
b1001000 +
1#
#380
0#
#381
b1000111 +
1#
#382
0#
#383
b1000110 +
1#
#384
0#
#385
b1000101 +
1#
#386
0#
#387
b1000100 +
1#
#388
0#
#389
b1000011 +
1#
#390
0#
#391
b1000010 +
1#
#392
0#
#393
b1000001 +
1#
#394
0#
#395
b1000000 +
1#
#396
0#
#397
b111111 +
1#
#398
0#
#399
b111110 +
1#
#400
0#
#401
b111101 +
1#
#402
0#
#403
b111100 +
1#
#404
0#
#405
b111011 +
1#
#406
0#
#407
b111010 +
1#
#408
0#
#409
b111001 +
1#
#410
0#
#411
b111000 +
1#
#412
0#
#413
b110111 +
1#
#414
0#
#415
b110110 +
1#
#416
0#
#417
b110101 +
1#
#418
0#
#419
b110100 +
1#
#420
0#
#421
b110011 +
1#
#422
0#
#423
b110010 +
1#
#424
0#
#425
b110001 +
1#
#426
0#
#427
b110000 +
1#
#428
0#
#429
b101111 +
1#
#430
0#
#431
b101110 +
1#
#432
0#
#433
b101101 +
1#
#434
0#
#435
b101100 +
1#
#436
0#
#437
b101011 +
1#
#438
0#
#439
b101010 +
1#
#440
0#
#441
b101001 +
1#
#442
0#
#443
b101000 +
1#
#444
0#
#445
b100111 +
1#
#446
0#
#447
b100110 +
1#
#448
0#
#449
b100101 +
1#
#450
0#
#451
b100100 +
1#
#452
0#
#453
b100011 +
1#
#454
0#
#455
b100010 +
1#
#456
0#
#457
b100001 +
1#
#458
0#
#459
b100000 +
1#
#460
0#
#461
b11111 +
1#
#462
0#
#463
b11110 +
1#
#464
0#
#465
b11101 +
1#
#466
0#
#467
b11100 +
1#
#468
0#
#469
b11011 +
1#
#470
0#
#471
b11010 +
1#
#472
0#
#473
b11001 +
1#
#474
0#
#475
b11000 +
1#
#476
0#
#477
b10111 +
1#
#478
0#
#479
b10110 +
1#
#480
0#
#481
b10101 +
1#
#482
0#
#483
b10100 +
1#
#484
0#
#485
b10011 +
1#
#486
0#
#487
b10010 +
1#
#488
0#
#489
b10001 +
1#
#490
0#
#491
b10000 +
1#
#492
0#
#493
b1111 +
1#
#494
0#
#495
b1110 +
1#
#496
0#
#497
b1101 +
1#
#498
0#
#499
b1100 +
1#
#500
0#
#501
b1011 +
1#
#502
0#
#503
b1010 +
1#
#504
0#
#505
b1001 +
1#
#506
0#
#507
b1000 +
1#
#508
0#
#509
b111 +
1#
#510
0#
#511
b110 +
1#
#512
0#
#513
b101 +
1#
#514
0#
#515
b100 +
1#
#516
0#
#517
b11 +
1#
#518
0#
#519
b10 +
1#
#520
0#
#521
b1 +
1#
#522
0#
#523
b0 +
1#
#524
0#
#525
b10 /
1#
#526
0#
#527
b1010011 ,
0!
0.
1#
#528
0#
#529
b1010010 ,
1#
#530
0#
#531
b1010001 ,
1#
#532
0#
#533
b1010000 ,
1#
#534
0#
#535
b1001111 ,
1#
#536
0#
#537
b1001110 ,
1#
#538
0#
#539
b1001101 ,
1#
#540
0#
#541
b1001100 ,
1#
#542
0#
#543
b1001011 ,
1#
#544
0#
#545
b1001010 ,
1#
#546
0#
#547
b1001001 ,
1#
#548
0#
#549
b1001000 ,
1#
#550
0#
#551
b1000111 ,
1#
#552
0#
#553
b1000110 ,
1#
#554
0#
#555
b1000101 ,
1#
#556
0#
#557
b1000100 ,
1#
#558
0#
#559
b1000011 ,
1#
#560
0#
#561
b1000010 ,
1#
#562
0#
#563
b1000001 ,
1#
#564
0#
#565
b1000000 ,
1#
#566
0#
#567
b111111 ,
1#
#568
0#
#569
b111110 ,
1#
#570
0#
#571
b111101 ,
1#
#572
0#
#573
b111100 ,
1#
#574
0#
#575
b111011 ,
1#
#576
0#
#577
b111010 ,
1#
#578
0#
#579
b111001 ,
1#
#580
0#
#581
b111000 ,
1#
#582
0#
#583
b110111 ,
1#
#584
0#
#585
b110110 ,
1#
#586
0#
#587
b110101 ,
1#
#588
0#
#589
b110100 ,
1#
#590
0#
#591
b110011 ,
1#
#592
0#
#593
b110010 ,
1#
#594
0#
#595
b110001 ,
1#
#596
0#
#597
b110000 ,
1#
#598
0#
#599
b101111 ,
1#
#600
0#
#601
b101110 ,
1#
#602
0#
#603
b101101 ,
1#
#604
0#
#605
b101100 ,
1#
#606
0#
#607
b101011 ,
1#
#608
0#
#609
b101010 ,
1#
#610
0#
#611
b101001 ,
1#
#612
0#
#613
b101000 ,
1#
#614
0#
#615
b100111 ,
1#
#616
0#
#617
b100110 ,
1#
#618
0#
#619
b100101 ,
1#
#620
0#
#621
b100100 ,
1#
#622
0#
#623
b100011 ,
1#
#624
0#
#625
b100010 ,
1#
#626
0#
#627
b100001 ,
1#
#628
0#
#629
b100000 ,
1#
#630
0#
#631
b11111 ,
1#
#632
0#
#633
b11110 ,
1#
#634
0#
#635
b11101 ,
1#
#636
0#
#637
b11100 ,
1#
#638
0#
#639
b11011 ,
1#
#640
0#
#641
b11010 ,
1#
#642
0#
#643
b11001 ,
1#
#644
0#
#645
b11000 ,
1#
#646
0#
#647
b10111 ,
1#
#648
0#
#649
b10110 ,
1#
#650
0#
#651
b10101 ,
1#
#652
0#
#653
b10100 ,
1#
#654
0#
#655
b10011 ,
1#
#656
0#
#657
b10010 ,
1#
#658
0#
#659
b10001 ,
1#
#660
0#
#661
b10000 ,
1#
#662
0#
#663
b1111 ,
1#
#664
0#
#665
b1110 ,
1#
#666
0#
#667
b1101 ,
1#
#668
0#
#669
b1100 ,
1#
#670
0#
#671
b1011 ,
1#
#672
0#
#673
b1010 ,
1#
#674
0#
#675
b1001 ,
1#
#676
0#
#677
b1000 ,
1#
#678
0#
#679
b111 ,
1#
#680
0#
#681
b110 ,
1#
#682
0#
#683
b101 ,
1#
#684
0#
#685
b100 ,
1#
#686
0#
#687
b11 ,
1#
#688
0#
#689
b10 ,
1#
#690
0#
#691
b1 ,
1#
#692
0#
#693
b0 ,
1#
#694
0#
#695
b0 /
b101010001000000 -
b1110 *
1#
#696
0#
#697
b1 /
b11010001 ,
b1111101 +
1#
#698
0#
#699
b1111100 +
1!
1.
1#
#700
0#
#701
b1111011 +
1#
#702
0#
#703
b1111010 +
1#
#704
0#
#705
b1111001 +
1#
#706
0#
#707
b1111000 +
1#
#708
0#
#709
b1110111 +
1#
#710
0#
#711
b1110110 +
1#
#712
0#
#713
b1110101 +
1#
#714
0#
#715
b1110100 +
1#
#716
0#
#717
b1110011 +
1#
#718
0#
#719
b1110010 +
1#
#720
0#
#721
b1110001 +
1#
#722
0#
#723
b1110000 +
1#
#724
0#
#725
b1101111 +
1#
#726
0#
#727
b1101110 +
1#
#728
0#
#729
b1101101 +
1#
#730
0#
#731
b1101100 +
1#
#732
0#
#733
b1101011 +
1#
#734
0#
#735
b1101010 +
1#
#736
0#
#737
b1101001 +
1#
#738
0#
#739
b1101000 +
1#
#740
0#
#741
b1100111 +
1#
#742
0#
#743
b1100110 +
1#
#744
0#
#745
b1100101 +
1#
#746
0#
#747
b1100100 +
1#
#748
0#
#749
b1100011 +
1#
#750
0#
#751
b1100010 +
1#
#752
0#
#753
b1100001 +
1#
#754
0#
#755
b1100000 +
1#
#756
0#
#757
b1011111 +
1#
#758
0#
#759
b1011110 +
1#
#760
0#
#761
b1011101 +
1#
#762
0#
#763
b1011100 +
1#
#764
0#
#765
b1011011 +
1#
#766
0#
#767
b1011010 +
1#
#768
0#
#769
b1011001 +
1#
#770
0#
#771
b1011000 +
1#
#772
0#
#773
b1010111 +
1#
#774
0#
#775
b1010110 +
1#
#776
0#
#777
b1010101 +
1#
#778
0#
#779
b1010100 +
1#
#780
0#
#781
b1010011 +
1#
#782
0#
#783
b1010010 +
1#
#784
0#
#785
b1010001 +
1#
#786
0#
#787
b1010000 +
1#
#788
0#
#789
b1001111 +
1#
#790
0#
#791
b1001110 +
1#
#792
0#
#793
b1001101 +
1#
#794
0#
#795
b1001100 +
1#
#796
0#
#797
b1001011 +
1#
#798
0#
#799
b1001010 +
1#
#800
0#
#801
b1001001 +
1#
#802
0#
#803
b1001000 +
1#
#804
0#
#805
b1000111 +
1#
#806
0#
#807
b1000110 +
1#
#808
0#
#809
b1000101 +
1#
#810
0#
#811
b1000100 +
1#
#812
0#
#813
b1000011 +
1#
#814
0#
#815
b1000010 +
1#
#816
0#
#817
b1000001 +
1#
#818
0#
#819
b1000000 +
1#
#820
0#
#821
b111111 +
1#
#822
0#
#823
b111110 +
1#
#824
0#
#825
b111101 +
1#
#826
0#
#827
b111100 +
1#
#828
0#
#829
b111011 +
1#
#830
0#
#831
b111010 +
1#
#832
0#
#833
b111001 +
1#
#834
0#
#835
b111000 +
1#
#836
0#
#837
b110111 +
1#
#838
0#
#839
b110110 +
1#
#840
0#
#841
b110101 +
1#
#842
0#
#843
b110100 +
1#
#844
0#
#845
b110011 +
1#
#846
0#
#847
b110010 +
1#
#848
0#
#849
b110001 +
1#
#850
0#
#851
b110000 +
1#
#852
0#
#853
b101111 +
1#
#854
0#
#855
b101110 +
1#
#856
0#
#857
b101101 +
1#
#858
0#
#859
b101100 +
1#
#860
0#
#861
b101011 +
1#
#862
0#
#863
b101010 +
1#
#864
0#
#865
b101001 +
1#
#866
0#
#867
b101000 +
1#
#868
0#
#869
b100111 +
1#
#870
0#
#871
b100110 +
1#
#872
0#
#873
b100101 +
1#
#874
0#
#875
b100100 +
1#
#876
0#
#877
b100011 +
1#
#878
0#
#879
b100010 +
1#
#880
0#
#881
b100001 +
1#
#882
0#
#883
b100000 +
1#
#884
0#
#885
b11111 +
1#
#886
0#
#887
b11110 +
1#
#888
0#
#889
b11101 +
1#
#890
0#
#891
b11100 +
1#
#892
0#
#893
b11011 +
1#
#894
0#
#895
b11010 +
1#
#896
0#
#897
b11001 +
1#
#898
0#
#899
b11000 +
1#
#900
0#
#901
b10111 +
1#
#902
0#
#903
b10110 +
1#
#904
0#
#905
b10101 +
1#
#906
0#
#907
b10100 +
1#
#908
0#
#909
b10011 +
1#
#910
0#
#911
b10010 +
1#
#912
0#
#913
b10001 +
1#
#914
0#
#915
b10000 +
1#
#916
0#
#917
b1111 +
1#
#918
0#
#919
b1110 +
1#
#920
0#
#921
b1101 +
1#
#922
0#
#923
b1100 +
1#
#924
0#
#925
b1011 +
1#
#926
0#
#927
b1010 +
1#
#928
0#
#929
b1001 +
1#
#930
0#
#931
b1000 +
1#
#932
0#
#933
b111 +
1#
#934
0#
#935
b110 +
1#
#936
0#
#937
b101 +
1#
#938
0#
#939
b100 +
1#
#940
0#
#941
b11 +
1#
#942
0#
#943
b10 +
1#
#944
0#
#945
b1 +
1#
#946
0#
#947
b0 +
1#
#948
0#
#949
b10 /
1#
#950
0#
#951
b11010000 ,
0!
0.
1#
#952
0#
#953
b11001111 ,
1#
#954
0#
#955
b11001110 ,
1#
#956
0#
#957
b11001101 ,
1#
#958
0#
#959
b11001100 ,
1#
#960
0#
#961
b11001011 ,
1#
#962
0#
#963
b11001010 ,
1#
#964
0#
#965
b11001001 ,
1#
#966
0#
#967
b11001000 ,
1#
#968
0#
#969
b11000111 ,
1#
#970
0#
#971
b11000110 ,
1#
#972
0#
#973
b11000101 ,
1#
#974
0#
#975
b11000100 ,
1#
#976
0#
#977
b11000011 ,
1#
#978
0#
#979
b11000010 ,
1#
#980
0#
#981
b11000001 ,
1#
#982
0#
#983
b11000000 ,
1#
#984
0#
#985
b10111111 ,
1#
#986
0#
#987
b10111110 ,
1#
#988
0#
#989
b10111101 ,
1#
#990
0#
#991
b10111100 ,
1#
#992
0#
#993
b10111011 ,
1#
#994
0#
#995
b10111010 ,
1#
#996
0#
#997
b10111001 ,
1#
#998
0#
#999
b10111000 ,
1#
#1000
0#
#1001
b10110111 ,
1#
#1002
0#
#1003
b10110110 ,
1#
#1004
0#
#1005
b10110101 ,
1#
#1006
0#
#1007
b10110100 ,
1#
#1008
0#
#1009
b10110011 ,
1#
#1010
0#
#1011
b10110010 ,
1#
#1012
0#
#1013
b10110001 ,
1#
#1014
0#
#1015
b10110000 ,
1#
#1016
0#
#1017
b10101111 ,
1#
#1018
0#
#1019
b10101110 ,
1#
#1020
0#
#1021
b10101101 ,
1#
#1022
0#
#1023
b10101100 ,
1#
#1024
0#
#1025
b10101011 ,
1#
#1026
0#
#1027
b10101010 ,
1#
#1028
0#
#1029
b10101001 ,
1#
#1030
0#
#1031
b10101000 ,
1#
#1032
0#
#1033
b10100111 ,
1#
#1034
0#
#1035
b10100110 ,
1#
#1036
0#
#1037
b10100101 ,
1#
#1038
0#
#1039
b10100100 ,
1#
#1040
0#
#1041
b10100011 ,
1#
#1042
0#
#1043
b10100010 ,
1#
#1044
0#
#1045
b10100001 ,
1#
#1046
0#
#1047
b10100000 ,
1#
#1048
0#
#1049
b10011111 ,
1#
#1050
0#
#1051
b10011110 ,
1#
#1052
0#
#1053
b10011101 ,
1#
#1054
0#
#1055
b10011100 ,
1#
#1056
0#
#1057
b10011011 ,
1#
#1058
0#
#1059
b10011010 ,
1#
#1060
0#
#1061
b10011001 ,
1#
#1062
0#
#1063
b10011000 ,
1#
#1064
0#
#1065
b10010111 ,
1#
#1066
0#
#1067
b10010110 ,
1#
#1068
0#
#1069
b10010101 ,
1#
#1070
0#
#1071
b10010100 ,
1#
#1072
0#
#1073
b10010011 ,
1#
#1074
0#
#1075
b10010010 ,
1#
#1076
0#
#1077
b10010001 ,
1#
#1078
0#
#1079
b10010000 ,
1#
#1080
0#
#1081
b10001111 ,
1#
#1082
0#
#1083
b10001110 ,
1#
#1084
0#
#1085
b10001101 ,
1#
#1086
0#
#1087
b10001100 ,
1#
#1088
0#
#1089
b10001011 ,
1#
#1090
0#
#1091
b10001010 ,
1#
#1092
0#
#1093
b10001001 ,
1#
#1094
0#
#1095
b10001000 ,
1#
#1096
0#
#1097
b10000111 ,
1#
#1098
0#
#1099
b10000110 ,
1#
#1100
0#
#1101
b10000101 ,
1#
#1102
0#
#1103
b10000100 ,
1#
#1104
0#
#1105
b10000011 ,
1#
#1106
0#
#1107
b10000010 ,
1#
#1108
0#
#1109
b10000001 ,
1#
#1110
0#
#1111
b10000000 ,
1#
#1112
0#
#1113
b1111111 ,
1#
#1114
0#
#1115
b1111110 ,
1#
#1116
0#
#1117
b1111101 ,
1#
#1118
0#
#1119
b1111100 ,
1#
#1120
0#
#1121
b1111011 ,
1#
#1122
0#
#1123
b1111010 ,
1#
#1124
0#
#1125
b1111001 ,
1#
#1126
0#
#1127
b1111000 ,
1#
#1128
0#
#1129
b1110111 ,
1#
#1130
0#
#1131
b1110110 ,
1#
#1132
0#
#1133
b1110101 ,
1#
#1134
0#
#1135
b1110100 ,
1#
#1136
0#
#1137
b1110011 ,
1#
#1138
0#
#1139
b1110010 ,
1#
#1140
0#
#1141
b1110001 ,
1#
#1142
0#
#1143
b1110000 ,
1#
#1144
0#
#1145
b1101111 ,
1#
#1146
0#
#1147
b1101110 ,
1#
#1148
0#
#1149
b1101101 ,
1#
#1150
0#
#1151
b1101100 ,
1#
#1152
0#
#1153
b1101011 ,
1#
#1154
0#
#1155
b1101010 ,
1#
#1156
0#
#1157
b1101001 ,
1#
#1158
0#
#1159
b1101000 ,
1#
#1160
0#
#1161
b1100111 ,
1#
#1162
0#
#1163
b1100110 ,
1#
#1164
0#
#1165
b1100101 ,
1#
#1166
0#
#1167
b1100100 ,
1#
#1168
0#
#1169
b1100011 ,
1#
#1170
0#
#1171
b1100010 ,
1#
#1172
0#
#1173
b1100001 ,
1#
#1174
0#
#1175
b1100000 ,
1#
#1176
0#
#1177
b1011111 ,
1#
#1178
0#
#1179
b1011110 ,
1#
#1180
0#
#1181
b1011101 ,
1#
#1182
0#
#1183
b1011100 ,
1#
#1184
0#
#1185
b1011011 ,
1#
#1186
0#
#1187
b1011010 ,
1#
#1188
0#
#1189
b1011001 ,
1#
#1190
0#
#1191
b1011000 ,
1#
#1192
0#
#1193
b1010111 ,
1#
#1194
0#
#1195
b1010110 ,
1#
#1196
0#
#1197
b1010101 ,
1#
#1198
0#
#1199
b1010100 ,
1#
#1200
0#
#1201
b1010011 ,
1#
#1202
0#
#1203
b1010010 ,
1#
#1204
0#
#1205
b1010001 ,
1#
#1206
0#
#1207
b1010000 ,
1#
#1208
0#
#1209
b1001111 ,
1#
#1210
0#
#1211
b1001110 ,
1#
#1212
0#
#1213
b1001101 ,
1#
#1214
0#
#1215
b1001100 ,
1#
#1216
0#
#1217
b1001011 ,
1#
#1218
0#
#1219
b1001010 ,
1#
#1220
0#
#1221
b1001001 ,
1#
#1222
0#
#1223
b1001000 ,
1#
#1224
0#
#1225
b1000111 ,
1#
#1226
0#
#1227
b1000110 ,
1#
#1228
0#
#1229
b1000101 ,
1#
#1230
0#
#1231
b1000100 ,
1#
#1232
0#
#1233
b1000011 ,
1#
#1234
0#
#1235
b1000010 ,
1#
#1236
0#
#1237
b1000001 ,
1#
#1238
0#
#1239
b1000000 ,
1#
#1240
0#
#1241
b111111 ,
1#
#1242
0#
#1243
b111110 ,
1#
#1244
0#
#1245
b111101 ,
1#
#1246
0#
#1247
b111100 ,
1#
#1248
0#
#1249
b111011 ,
1#
#1250
0#
#1251
b111010 ,
1#
#1252
0#
#1253
b111001 ,
1#
#1254
0#
#1255
b111000 ,
1#
#1256
0#
#1257
b110111 ,
1#
#1258
0#
#1259
b110110 ,
1#
#1260
0#
#1261
b110101 ,
1#
#1262
0#
#1263
b110100 ,
1#
#1264
0#
#1265
b110011 ,
1#
#1266
0#
#1267
b110010 ,
1#
#1268
0#
#1269
b110001 ,
1#
#1270
0#
#1271
b110000 ,
1#
#1272
0#
#1273
b101111 ,
1#
#1274
0#
#1275
b101110 ,
1#
#1276
0#
#1277
b101101 ,
1#
#1278
0#
#1279
b101100 ,
1#
#1280
0#
#1281
b101011 ,
1#
#1282
0#
#1283
b101010 ,
1#
#1284
0#
#1285
b101001 ,
1#
#1286
0#
#1287
b101000 ,
1#
#1288
0#
#1289
b100111 ,
1#
#1290
0#
